aivm/README.md
aivm/__init__.py
aivm/benchmark/__init__.py
aivm/benchmark/csv_logger.py
aivm/launcher.py
aivm/models/__init__.py
aivm/models/cnn.py
aivm/models/cnn_models/__init__.py
aivm/models/cnn_models/lenet5.pth
aivm/models/cnn_models/lenet5.py
aivm/models/llm.py
aivm/models/llm_models/__init__.py
aivm/models/llm_models/bert.py
aivm/models/llm_models/bert_for_sequence_classification.py
aivm/models/llm_models/gpt.py
aivm/models/mesh_keep_alive_model/__init__.py
aivm/models/mesh_keep_alive_model/mesh_keep_alive.py
aivm/models/model_benchmark.py
aivm/models/onnx.py
aivm/models/onnx_models/__init__.py
aivm/models/onnx_models/bert_tiny_sms.py
aivm/models/utils.py
aivm/pyproject.toml
aivm/server/__init__.py
aivm/server/client_servicer.py
aivm/server/model_servicer.py
aivm/server/network.py
aivm/server/preprocessing.py
aivm/server_loop.py
aivm/test_client/__init__.py
aivm/test_client/client.py
aivm/ttp.py
aivm_client/README.md
aivm_client/__init__.py
aivm_client/bert_tiny_tokenizer.py
aivm_client/client.py
aivm_client/model.py
aivm_client/pyproject.toml
aivm_config/README.md
aivm_config/__init__.py
aivm_config/config/__init__.py
aivm_config/config/global.yaml
aivm_config/global_config.py
aivm_config/launch_config/__init__.py
aivm_config/launch_config/aws.yaml
aivm_config/launch_config/docker_compose_config.yaml
aivm_config/launch_config/docker_local.yaml
aivm_config/launch_config/localhost.yaml
aivm_config/launch_config_gen.py
aivm_config/logging/__init__.py
aivm_config/logging/logger.py
aivm_config/pyproject.toml
aivm_proxy/README.md
aivm_proxy/__init__.py
aivm_proxy/proxy_servicer.py
aivm_proxy/pyproject.toml
aivm_grpc/README.md
aivm_grpc/__init__.py
aivm_grpc/pyproject.toml
aivm_grpc/share_service.proto
aivm_grpc/share_service_pb2.py
aivm_grpc/share_service_pb2_grpc.py
aivm_grpc/test/client.py
aivm_grpc/test/healthcheck.py
aivm_grpc/test/proxy.py
aivm_grpc/test/server.py
curl/README.md
curl/__init__.py
curl/autograd_cryptensor.py
curl/benchmarks/__init__.py
nillion_aivm-0.1.4.dist-info/LICENSE
nillion_aivm-0.1.4.dist-info/METADATA
nillion_aivm-0.1.4.dist-info/WHEEL
nillion_aivm-0.1.4.dist-info/entry_points.txt
nillion_aivm-0.1.4.dist-info/RECORD
