Metadata-Version: 2.1
Name: nillion-aivm
Version: 0.1.4
Summary: AIVM: secure infrastructure for running MLaaS.
Author: José Cabrero-Holgueras
Author-email: jose.cabrero@nillion.com
Requires-Python: >=3.10,<4.0
Classifier: Programming Language :: Python :: 3
Classifier: Programming Language :: Python :: 3.10
Classifier: Programming Language :: Python :: 3.11
Classifier: Programming Language :: Python :: 3.12
Classifier: Programming Language :: Python :: 3.13
Provides-Extra: examples
Requires-Dist: datasets (>=3.0.1,<4.0.0) ; extra == "examples"
Requires-Dist: future (>=1.0.0,<2.0.0)
Requires-Dist: googleapis-common-protos (>=1.65.0,<2.0.0)
Requires-Dist: grpcio (>=1.66.1,<2.0.0)
Requires-Dist: grpcio-tools (>=1.66.1,<2.0.0)
Requires-Dist: matplotlib (>=3.9.2,<4.0.0) ; extra == "examples"
Requires-Dist: numpy (>=1.26.4,<2.0.0)
Requires-Dist: omegaconf (>=2.0.6)
Requires-Dist: onnx (>=1.17.0,<2.0.0)
Requires-Dist: onnxruntime (>=1.19.2,<2.0.0) ; extra == "examples"
Requires-Dist: pandas (>=1.2.2)
Requires-Dist: pywavelets (>=1.7.0)
Requires-Dist: pyyaml (>=6.0.2,<7.0.0)
Requires-Dist: scikit-learn (>=1.5.1,<2.0.0)
Requires-Dist: scipy (>=1.6.0)
Requires-Dist: tensorboard (>=2.17.1,<3.0.0)
Requires-Dist: torch (>=2.4.1,<3.0.0)
Requires-Dist: torchvision (>=0.19.1,<0.20.0)
Requires-Dist: transformers (>=4.45.2,<5.0.0)
Requires-Dist: visdom (>=0.2.4,<0.3.0)
